pyQEdark/__init__.py
pyQEdark/constants.py
pyQEdark/crystaldme.py
pyQEdark/dmvdf.py
pyQEdark/etas.py
pyQEdark/plotting.py
pyQEdark/stats.py
pyQEdark/vdfs.py
pyQEdark/QEdark_data/Ge_f2.txt
pyQEdark/QEdark_data/Si_f2.txt
pyQEdark/vdfparams/__init__.py
pyQEdark/vdfparams/kms.py
pyQEdark/vdfparams/nat.py
pyQEdark-0.1.2.dist-info/LICENSE.md
pyQEdark-0.1.2.dist-info/METADATA
pyQEdark-0.1.2.dist-info/WHEEL
pyQEdark-0.1.2.dist-info/top_level.txt
pyQEdark-0.1.2.dist-info/RECORD
