Metadata-Version: 2.1
Name: pyQEdark
Version: 0.1.2
Summary: A python package for analyzing output files from QEdark
Home-page: https://github.com/ariaradick/pyQEdark
Author: Aria Radick
Author-email: aradick@uoregon.edu
License: UNKNOWN
Project-URL: Bug Tracker, https://github.com/ariaradick/pyQEdark/issues
Platform: UNKNOWN
Classifier: Programming Language :: Python :: 3
Classifier: License :: OSI Approved :: GNU General Public License v3 (GPLv3)
Classifier: Operating System :: OS Independent
Requires-Python: >=3.6
License-File: LICENSE.md
Requires-Dist: numpy
Requires-Dist: scipy
Requires-Dist: matplotlib
